findrum/__init__.py
findrum/__main__.py
findrum/engine/__init__.py
findrum/engine/pipeline_runner.py
findrum/engine/platform.py
findrum/interfaces/__init__.py
findrum/interfaces/data_source.py
findrum/interfaces/event_trigger.py
findrum/interfaces/operator.py
findrum/interfaces/scheduler.py
findrum/loader/__init__.py
findrum/loader/load_extensions.py
findrum/registry/__init__.py
findrum/registry/registry.py
findrum_platform-1.2.2.dist-info/licenses/LICENSE
findrum_platform-1.2.2.dist-info/METADATA
findrum_platform-1.2.2.dist-info/WHEEL
findrum_platform-1.2.2.dist-info/entry_points.txt
findrum_platform-1.2.2.dist-info/top_level.txt
findrum_platform-1.2.2.dist-info/RECORD
