Metadata-Version: 2.4
Name: findrum-platform
Version: 1.2.2
Summary: Framework for building modular, event-driven data pipelines
Author-email: Óscar <oscar.rico101@alu.ulpgc.es>
Requires-Python: >=3.12
License-File: LICENSE
Requires-Dist: APScheduler==3.11.0
Requires-Dist: pandas==2.2.3
Requires-Dist: PyYAML==6.0.2
Requires-Dist: python-dateutil==2.9.0.post0
Provides-Extra: dev
Requires-Dist: pytest; extra == "dev"
Requires-Dist: pytest-cov; extra == "dev"
Dynamic: license-file
